Metadata-Version: 2.1
Name: configtoolkit
Version: 0.1.2
Summary: Another configuration library
Home-page: https://github.com/xenocorn/configtoolkit
Author: XenoCorn
License: UNKNOWN
Platform: UNKNOWN
Classifier: Programming Language :: Python :: 3.7
Classifier: License :: OSI Approved :: BSD License
